<?xml version="1.0" encoding="utf-8" ?>
<dwsync>
<file name="ratchicons.eot" server="www.mmtmobile.org" local="130557231220000000" remote="130666501800000000" Dst="1" />
<file name="ratchicons.ttf" server="www.mmtmobile.org" local="130557231220000000" remote="130666501800000000" Dst="1" />
<file name="ratchicons_old.eot" server="www.mmtmobile.org" local="130408905980000000" remote="130666501800000000" Dst="1" />
<file name="ratchicons.woff" server="www.mmtmobile.org" local="130557231220000000" remote="130666501800000000" Dst="1" />
<file name="ratchicons_old.svg" server="www.mmtmobile.org" local="130408905980000000" remote="130666501800000000" Dst="1" />
<file name="ratchicons_old.ttf" server="www.mmtmobile.org" local="130408905980000000" remote="130666501800000000" Dst="1" />
<file name="ratchicons_old.woff" server="www.mmtmobile.org" local="130408905980000000" remote="130666501800000000" Dst="1" />
<file name="ratchicons.svg" server="www.mmtmobile.org" local="130557231220000000" remote="130666501800000000" Dst="1" />
</dwsync>